32bit_PIPO.v
module pipomod_32bit (
  input clk,    // Clock signal
  input clear,  // Clear signal
  input [31:0] pi,  // Parallel input data
  output reg [31:0] po  // Parallel output data
);

  always @(posedge clk) begin
    if (clear) begin
      po <= 32'b0;  // Clear the shift register
    end else begin
      po[31:1] <= pi[30:0]; 
      po[0] <= 1'b0;
    end
  end

endmodule

tb_32bit_PIPO.v
module pipomod_32bit_tb;
  reg clk;              
  reg clear;           
  reg [31:0] pi;      
  wire [31:0] po;    

  pipomod_32bit uut (
    .clk(clk),
    .clear(clear),
    .pi(pi),
    .po(po)
  );

  always begin
    #5 clk = ~clk;
  end

  initial begin
    $dumpfile("out.vcd");  
    $dumpvars(0, pipomod_32bit_tb); 

    $monitor("Time=%0t clk=%b clear=%b po=%b pi=%b", $time, clk, clear, po, pi);

    clk = 0;
    clear = 0;
    pi = 32'b0;

    #5 clear = 1'b1;
    #5 clear = 1'b0;

    #10 pi = 32'b1001;
    #10 pi = 32'b1010;
    #10 pi = 32'b1011;
    #10 pi = 32'b1110;
    #10 pi = 32'b1111;
    #10 pi = 32'b0000;
    $finish;
  end
endmodule

out.vcd
$date
	Fri Nov 24 00:07:52 2023
$end
$version
	Icarus Verilog
$end
$timescale
	1s
$end
$scope module pipomod_32bit_tb $end
$var wire 32 ! po [31:0] $end
$var reg 1 " clear $end
$var reg 1 # clk $end
$var reg 32 $ pi [31:0] $end
$scope module uut $end
$var wire 1 % clear $end
$var wire 1 & clk $end
$var wire 32 ' pi [31:0] $end
$var reg 32 ( po [31:0] $end
$upscope $end
$upscope $end
$enddefinitions $end
#0
$dumpvars
bx (
b0 '
0&
0%
b0 $
0#
0"
bx !
$end
#5
b0 (
b0 !
1"
1%
1#
1&
#10
0"
0%
0#
0&
#15
b0 (
1#
1&
#20
0#
0&
b1001 $
b1001 '
#25
b10010 (
b10010 !
1#
1&
#30
0#
0&
b1010 $
b1010 '
#35
b10100 (
b10100 !
1#
1&
#40
0#
0&
b1011 $
b1011 '
#45
b10110 (
b10110 !
1#
1&
#50
0#
0&
b1110 $
b1110 '
#55
b11100 (
b11100 !
1#
1&
#60
0#
0&
b1111 $
b1111 '
#65
b11110 (
b11110 !
1#
1&
#70
0#
0&
b0 $
b0 '
